.hgignore
.hgtags
.project
.pydevproject
CHANGES.txt
MANIFEST.in
README.txt
ez_setup.py
setup.cfg
setup.py
src/tri/__init__.py
src/tri/delaunay.py
src/tri/voronoi.py
src/tri.egg-info/PKG-INFO
src/tri.egg-info/SOURCES.txt
src/tri.egg-info/dependency_links.txt
src/tri.egg-info/not-zip-safe
src/tri.egg-info/requires.txt
src/tri.egg-info/top_level.txt