Metadata-Version: 1.1
Name: tri
Version: 0.3
Summary: (Constrained) Delaunay Triangulation of Planar Straight Line Graphs (pure Python)
Home-page: https://bitbucket.org/bmmeijers/tri/
Author: Martijn Meijers
Author-email: b.m.meijers@tudelft.nl
License: MIT license
Platform: UNKNOWN
Classifier: Development Status :: 4 - Beta
Classifier: Intended Audience :: Developers
Classifier: Intended Audience :: Information Technology
Classifier: License :: OSI Approved :: MIT License
Classifier: Operating System :: OS Independent
Classifier: Programming Language :: Python
Classifier: Programming Language :: Python :: 2.7
Classifier: Topic :: Software Development :: Libraries
Classifier: Topic :: Software Development :: Libraries :: Python Modules
Classifier: Topic :: Scientific/Engineering :: GIS
Classifier: Topic :: Scientific/Engineering :: Information Analysis
